Workbook

Sheet README
A1: Restaurant CFO
A2: A Financial Intelligence Toolkit for Restaurants — not just a calculator.
B4: What this workbook does
B5: Purpose | C5: Turns your raw restaurant numbers (ingredients, recipes, expenses, sales) into pricing decisions, a profitability score, and a prioritized action list.
B7: Color guide
B8: Blue text / yellow fill | C8: Cells you edit — your own data goes here.
B9: Black text | C9: Formulas — do not overwrite, they recalculate automatically.
B10: Green text | C10: Values pulled automatically from another sheet.
B12: Workflow (do this in order)
C13: 1. Business Profile — set your currency, VAT, targets and working days.
C14: 2. Ingredients Database — list every raw ingredient and its purchase price.
C15: 3. Recipe Builder — build each menu item's recipe from those ingredients.
C16: 4. Packaging — add packaging cost per menu item.
C17: 5. Operating Expenses — enter fixed monthly overhead (rent, salaries, etc.).
C18: 6. Menu Pricing — set selling prices; review the auto-calculated margins and status.
C19: 7. Sales — log daily sales by item (or paste from your POS export).
C20: 8. Everything downstream (Dashboard, Health Score, Menu Engineering, Profit Leakage,
C21: Recommendations) recalculates automatically — nothing else to enter.
B23: Recommended update frequency
B24: Sales | C24: Daily or weekly (paste from POS)
B25: Ingredients / purchase prices | C25: Whenever a supplier price changes
B26: Recipe Builder | C26: When a recipe changes
B27: Operating Expenses | C27: Monthly
B28: Menu Pricing review | C28: Monthly — check the Profit Status column
B30: Included in this version
C31: Business Profile, Ingredients Database, Recipe Builder, Packaging, Operating Expenses,
C32: Menu Pricing, Sales, Inventory Summary, Dashboard, Restaurant Health Score,
C33: Menu Engineering, Profit Leakage, and Recommendations.
B35: Not yet built (available on request)
C36: Scenario Simulator, Opportunity Score, and the printable Executive Report.
B37: Notes on formulas
C38: This workbook uses INDEX/MATCH and SUMIFS rather than XLOOKUP/FILTER/SORT, so every formula recalculates correctly in any version of Excel or LibreOffice.

Sheet Business Profile
A1: Business Profile
A2: Core settings used across the whole workbook.
A4: Field | B4: Value
A5: Business Name
A6: Currency | B6: USD
A7: VAT % | B7: 0.08
A8: Working Days per Month | B8: 26
A9: Target Food Cost % | B9: 0.3
A10: Target Gross Margin % | B10: 0.65
A11: Target Net Margin % | B11: 0.15
A12: Target Monthly Profit | B12: 0
A13: Expected Monthly Revenue | B13: 0
A14: Average Daily Orders | B14: 0
A15: Average Items per Order | B15: 2
A16: Average Ticket Size (calculated) | B16: =IFERROR(B13/(B8*B14),0) -> 0

Sheet Dashboard
A1: Executive Dashboard
A2: Restaurant CFO — live snapshot
A4: Total Revenue (period) | C4: Total Gross Profit (period) | E4: Total Net Profit (period) | G4: Average Food Cost %
A5: =SUM(Sales!$D$5:$D$124) -> 0 | C5: =SUM(Sales!$E$5:$E$124) -> 0 | E5: =SUM(Sales!$F$5:$F$124) -> 0 | G5: =AVERAGE('Menu Pricing'!$O$5:$O$10) -> 0
A8: Average Net Margin % | C8: Average Profit per Sale | E8: Monthly Estimated Profit | G8: Restaurant Health Score
A9: =AVERAGE('Menu Pricing'!$N$5:$N$10) -> 0 | C9: =IFERROR(SUM(Sales!$F$5:$F$124)/SUM(Sales!$C$5:$C$124),0) -> 0 | E9: =IFERROR(SUM(Sales!$F$5:$F$124)/(Sales!$A$124-Sales!$A$5+1)*'Business Profile'!$B$8,0) -> 0 | G9: ='Restaurant Health Score'!$D$16 -> 65
A14: Menu Item | B14: Revenue | C14: Net Profit | D14: Units Sold
A15: ='Menu Pricing'!A5 -> Menu Item 1 | B15: =SUMIFS(Sales!$D$5:$D$124,Sales!$B$5:$B$124,A15) -> 0 | C15: =SUMIFS(Sales!$F$5:$F$124,Sales!$B$5:$B$124,A15) -> 0 | D15: =SUMIFS(Sales!$C$5:$C$124,Sales!$B$5:$B$124,A15) -> 0
A16: ='Menu Pricing'!A6 -> Menu Item 2 | B16: =SUMIFS(Sales!$D$5:$D$124,Sales!$B$5:$B$124,A16) -> 0 | C16: =SUMIFS(Sales!$F$5:$F$124,Sales!$B$5:$B$124,A16) -> 0 | D16: =SUMIFS(Sales!$C$5:$C$124,Sales!$B$5:$B$124,A16) -> 0
A17: ='Menu Pricing'!A7 -> Menu Item 3 | B17: =SUMIFS(Sales!$D$5:$D$124,Sales!$B$5:$B$124,A17) -> 0 | C17: =SUMIFS(Sales!$F$5:$F$124,Sales!$B$5:$B$124,A17) -> 0 | D17: =SUMIFS(Sales!$C$5:$C$124,Sales!$B$5:$B$124,A17) -> 0
A18: ='Menu Pricing'!A8 -> Menu Item 4 | B18: =SUMIFS(Sales!$D$5:$D$124,Sales!$B$5:$B$124,A18) -> 0 | C18: =SUMIFS(Sales!$F$5:$F$124,Sales!$B$5:$B$124,A18) -> 0 | D18: =SUMIFS(Sales!$C$5:$C$124,Sales!$B$5:$B$124,A18) -> 0
A19: ='Menu Pricing'!A9 -> Menu Item 5 | B19: =SUMIFS(Sales!$D$5:$D$124,Sales!$B$5:$B$124,A19) -> 0 | C19: =SUMIFS(Sales!$F$5:$F$124,Sales!$B$5:$B$124,A19) -> 0 | D19: =SUMIFS(Sales!$C$5:$C$124,Sales!$B$5:$B$124,A19) -> 0
A20: ='Menu Pricing'!A10 -> Menu Item 6 | B20: =SUMIFS(Sales!$D$5:$D$124,Sales!$B$5:$B$124,A20) -> 0 | C20: =SUMIFS(Sales!$F$5:$F$124,Sales!$B$5:$B$124,A20) -> 0 | D20: =SUMIFS(Sales!$C$5:$C$124,Sales!$B$5:$B$124,A20) -> 0

Sheet Ingredients Database
A1: Ingredients Database
A2: Every raw ingredient, priced back to a usable cost per gram / piece / liter.
A4: Ingredient | B4: Category | C4: Supplier | D4: Purchase Unit | E4: Package Size | F4: Purchase Price | G4: Waste % | H4: Yield % | I4: Current Stock | J4: Minimum Stock | K4: Real Unit Cost | L4: Cost per Gram | M4: Cost per Piece | N4: Cost per Liter | O4: Last Purchase Date | P4: Notes
A5: Ingredient 1 | E5: 1 | F5: 0 | G5: 0 | H5: 1 | I5: 0 | J5: 0 | K5: =IFERROR(F5/E5/H5,0) -> 0 | L5: =IF(D5="kg",K5/1000,IF(D5="g",K5,"")) | M5: =IF(D5="piece",K5,"") | N5: =IF(D5="l",K5,"") | O5: 46227
A6: Ingredient 2 | E6: 1 | F6: 0 | G6: 0 | H6: 1 | I6: 0 | J6: 0 | K6: =IFERROR(F6/E6/H6,0) -> 0 | L6: =IF(D6="kg",K6/1000,IF(D6="g",K6,"")) | M6: =IF(D6="piece",K6,"") | N6: =IF(D6="l",K6,"") | O6: 46226
A7: Ingredient 3 | E7: 1 | F7: 0 | G7: 0 | H7: 1 | I7: 0 | J7: 0 | K7: =IFERROR(F7/E7/H7,0) -> 0 | L7: =IF(D7="kg",K7/1000,IF(D7="g",K7,"")) | M7: =IF(D7="piece",K7,"") | N7: =IF(D7="l",K7,"") | O7: 46225
A8: Ingredient 4 | E8: 1 | F8: 0 | G8: 0 | H8: 1 | I8: 0 | J8: 0 | K8: =IFERROR(F8/E8/H8,0) -> 0 | L8: =IF(D8="kg",K8/1000,IF(D8="g",K8,"")) | M8: =IF(D8="piece",K8,"") | N8: =IF(D8="l",K8,"") | O8: 46224
A9: Ingredient 5 | E9: 1 | F9: 0 | G9: 0 | H9: 1 | I9: 0 | J9: 0 | K9: =IFERROR(F9/E9/H9,0) -> 0 | L9: =IF(D9="kg",K9/1000,IF(D9="g",K9,"")) | M9: =IF(D9="piece",K9,"") | N9: =IF(D9="l",K9,"") | O9: 46223
A10: Ingredient 6 | E10: 1 | F10: 0 | G10: 0 | H10: 1 | I10: 0 | J10: 0 | K10: =IFERROR(F10/E10/H10,0) -> 0 | L10: =IF(D10="kg",K10/1000,IF(D10="g",K10,"")) | M10: =IF(D10="piece",K10,"") | N10: =IF(D10="l",K10,"") | O10: 46222
A11: Ingredient 7 | E11: 1 | F11: 0 | G11: 0 | H11: 1 | I11: 0 | J11: 0 | K11: =IFERROR(F11/E11/H11,0) -> 0 | L11: =IF(D11="kg",K11/1000,IF(D11="g",K11,"")) | M11: =IF(D11="piece",K11,"") | N11: =IF(D11="l",K11,"") | O11: 46221
A12: Ingredient 8 | E12: 1 | F12: 0 | G12: 0 | H12: 1 | I12: 0 | J12: 0 | K12: =IFERROR(F12/E12/H12,0) -> 0 | L12: =IF(D12="kg",K12/1000,IF(D12="g",K12,"")) | M12: =IF(D12="piece",K12,"") | N12: =IF(D12="l",K12,"") | O12: 46220
A13: Ingredient 9 | E13: 1 | F13: 0 | G13: 0 | H13: 1 | I13: 0 | J13: 0 | K13: =IFERROR(F13/E13/H13,0) -> 0 | L13: =IF(D13="kg",K13/1000,IF(D13="g",K13,"")) | M13: =IF(D13="piece",K13,"") | N13: =IF(D13="l",K13,"") | O13: 46219
A14: Ingredient 10 | E14: 1 | F14: 0 | G14: 0 | H14: 1 | I14: 0 | J14: 0 | K14: =IFERROR(F14/E14/H14,0) -> 0 | L14: =IF(D14="kg",K14/1000,IF(D14="g",K14,"")) | M14: =IF(D14="piece",K14,"") | N14: =IF(D14="l",K14,"") | O14: 46218
A15: Ingredient 11 | E15: 1 | F15: 0 | G15: 0 | H15: 1 | I15: 0 | J15: 0 | K15: =IFERROR(F15/E15/H15,0) -> 0 | L15: =IF(D15="kg",K15/1000,IF(D15="g",K15,"")) | M15: =IF(D15="piece",K15,"") | N15: =IF(D15="l",K15,"") | O15: 46217
A16: Ingredient 12 | E16: 1 | F16: 0 | G16: 0 | H16: 1 | I16: 0 | J16: 0 | K16: =IFERROR(F16/E16/H16,0) -> 0 | L16: =IF(D16="kg",K16/1000,IF(D16="g",K16,"")) | M16: =IF(D16="piece",K16,"") | N16: =IF(D16="l",K16,"") | O16: 46216

Sheet Recipe Builder
A1: Recipe Builder
A2: Line-by-line recipes. Ingredient cost pulls automatically from Ingredients Database.
A4: Recipe Name | B4: Category | C4: Ingredient | D4: Quantity | E4: Unit | F4: Ingredient Cost | G4: Portion Weight (g) | H4: Recipe Notes
A5: Menu Item 1 | D5: 0 | F5: =IFERROR($D5*IF($E5="g",INDEX('Ingredients Database'!$L$5:$L$16,MATCH($C5,'Ingredients Database'!$A$5:$A$16,0)),IF($E5="piece",INDEX('Ingredients Database'!$M$5:$M$16,MATCH($C5,'Ingredients Database'!$A$5:$A$16,0)),IF($E5="l",INDEX('Ingredients Database'!$N$5:$N$16,MATCH($C5,'Ingredients Database'!$A$5:$A$16,0)),0))),0) -> 0 | G5: =IF($E5="g",$D5,"")
A6: Menu Item 1 | D6: 0 | F6: =IFERROR($D6*IF($E6="g",INDEX('Ingredients Database'!$L$5:$L$16,MATCH($C6,'Ingredients Database'!$A$5:$A$16,0)),IF($E6="piece",INDEX('Ingredients Database'!$M$5:$M$16,MATCH($C6,'Ingredients Database'!$A$5:$A$16,0)),IF($E6="l",INDEX('Ingredients Database'!$N$5:$N$16,MATCH($C6,'Ingredients Database'!$A$5:$A$16,0)),0))),0) -> 0 | G6: =IF($E6="g",$D6,"")
A7: Menu Item 1 | D7: 0 | F7: =IFERROR($D7*IF($E7="g",INDEX('Ingredients Database'!$L$5:$L$16,MATCH($C7,'Ingredients Database'!$A$5:$A$16,0)),IF($E7="piece",INDEX('Ingredients Database'!$M$5:$M$16,MATCH($C7,'Ingredients Database'!$A$5:$A$16,0)),IF($E7="l",INDEX('Ingredients Database'!$N$5:$N$16,MATCH($C7,'Ingredients Database'!$A$5:$A$16,0)),0))),0) -> 0 | G7: =IF($E7="g",$D7,"")
A8: Menu Item 1 | D8: 0 | F8: =IFERROR($D8*IF($E8="g",INDEX('Ingredients Database'!$L$5:$L$16,MATCH($C8,'Ingredients Database'!$A$5:$A$16,0)),IF($E8="piece",INDEX('Ingredients Database'!$M$5:$M$16,MATCH($C8,'Ingredients Database'!$A$5:$A$16,0)),IF($E8="l",INDEX('Ingredients Database'!$N$5:$N$16,MATCH($C8,'Ingredients Database'!$A$5:$A$16,0)),0))),0) -> 0 | G8: =IF($E8="g",$D8,"")
A9: Menu Item 1 | D9: 0 | F9: =IFERROR($D9*IF($E9="g",INDEX('Ingredients Database'!$L$5:$L$16,MATCH($C9,'Ingredients Database'!$A$5:$A$16,0)),IF($E9="piece",INDEX('Ingredients Database'!$M$5:$M$16,MATCH($C9,'Ingredients Database'!$A$5:$A$16,0)),IF($E9="l",INDEX('Ingredients Database'!$N$5:$N$16,MATCH($C9,'Ingredients Database'!$A$5:$A$16,0)),0))),0) -> 0 | G9: =IF($E9="g",$D9,"")
A10: Menu Item 2 | D10: 0 | F10: =IFERROR($D10*IF($E10="g",INDEX('Ingredients Database'!$L$5:$L$16,MATCH($C10,'Ingredients Database'!$A$5:$A$16,0)),IF($E10="piece",INDEX('Ingredients Database'!$M$5:$M$16,MATCH($C10,'Ingredients Database'!$A$5:$A$16,0)),IF($E10="l",INDEX('Ingredients Database'!$N$5:$N$16,MATCH($C10,'Ingredients Database'!$A$5:$A$16,0)),0))),0) -> 0 | G10: =IF($E10="g",$D10,"")
A11: Menu Item 2 | D11: 0 | F11: =IFERROR($D11*IF($E11="g",INDEX('Ingredients Database'!$L$5:$L$16,MATCH($C11,'Ingredients Database'!$A$5:$A$16,0)),IF($E11="piece",INDEX('Ingredients Database'!$M$5:$M$16,MATCH($C11,'Ingredients Database'!$A$5:$A$16,0)),IF($E11="l",INDEX('Ingredients Database'!$N$5:$N$16,MATCH($C11,'Ingredients Database'!$A$5:$A$16,0)),0))),0) -> 0 | G11: =IF($E11="g",$D11,"")
A12: Menu Item 2 | D12: 0 | F12: =IFERROR($D12*IF($E12="g",INDEX('Ingredients Database'!$L$5:$L$16,MATCH($C12,'Ingredients Database'!$A$5:$A$16,0)),IF($E12="piece",INDEX('Ingredients Database'!$M$5:$M$16,MATCH($C12,'Ingredients Database'!$A$5:$A$16,0)),IF($E12="l",INDEX('Ingredients Database'!$N$5:$N$16,MATCH($C12,'Ingredients Database'!$A$5:$A$16,0)),0))),0) -> 0 | G12: =IF($E12="g",$D12,"")
A13: Menu Item 2 | D13: 0 | F13: =IFERROR($D13*IF($E13="g",INDEX('Ingredients Database'!$L$5:$L$16,MATCH($C13,'Ingredients Database'!$A$5:$A$16,0)),IF($E13="piece",INDEX('Ingredients Database'!$M$5:$M$16,MATCH($C13,'Ingredients Database'!$A$5:$A$16,0)),IF($E13="l",INDEX('Ingredients Database'!$N$5:$N$16,MATCH($C13,'Ingredients Database'!$A$5:$A$16,0)),0))),0) -> 0 | G13: =IF($E13="g",$D13,"")
A14: Menu Item 3 | D14: 0 | F14: =IFERROR($D14*IF($E14="g",INDEX('Ingredients Database'!$L$5:$L$16,MATCH($C14,'Ingredients Database'!$A$5:$A$16,0)),IF($E14="piece",INDEX('Ingredients Database'!$M$5:$M$16,MATCH($C14,'Ingredients Database'!$A$5:$A$16,0)),IF($E14="l",INDEX('Ingredients Database'!$N$5:$N$16,MATCH($C14,'Ingredients Database'!$A$5:$A$16,0)),0))),0) -> 0 | G14: =IF($E14="g",$D14,"")
A15: Menu Item 3 | D15: 0 | F15: =IFERROR($D15*IF($E15="g",INDEX('Ingredients Database'!$L$5:$L$16,MATCH($C15,'Ingredients Database'!$A$5:$A$16,0)),IF($E15="piece",INDEX('Ingredients Database'!$M$5:$M$16,MATCH($C15,'Ingredients Database'!$A$5:$A$16,0)),IF($E15="l",INDEX('Ingredients Database'!$N$5:$N$16,MATCH($C15,'Ingredients Database'!$A$5:$A$16,0)),0))),0) -> 0 | G15: =IF($E15="g",$D15,"")
A16: Menu Item 3 | D16: 0 | F16: =IFERROR($D16*IF($E16="g",INDEX('Ingredients Database'!$L$5:$L$16,MATCH($C16,'Ingredients Database'!$A$5:$A$16,0)),IF($E16="piece",INDEX('Ingredients Database'!$M$5:$M$16,MATCH($C16,'Ingredients Database'!$A$5:$A$16,0)),IF($E16="l",INDEX('Ingredients Database'!$N$5:$N$16,MATCH($C16,'Ingredients Database'!$A$5:$A$16,0)),0))),0) -> 0 | G16: =IF($E16="g",$D16,"")
... A24: Menu Item 6 | D24: 0 | F24: =IFERROR($D24*IF($E24="g",INDEX('Ingredients Database'!$L$5:$L$16,MATCH($C24,'Ingredients Database'!$A$5:$A$16,0)),IF($E24="piece",INDEX('Ingredients Database'!$M$5:$M$16,MATCH($C24,'Ingredients Database'!$A$5:$A$16,0)),IF($E24="l",INDEX('Ingredients Database'!$N$5:$N$16,MATCH($C24,'Ingredients Database'!$A$5:$A$16,0)),0))),0) -> 0 | G24: =IF($E24="g",$D24,"")
A27: Recipe Cost Summary
A28: Recipe Name | B28: Category | C28: Total Recipe Cost | D28: Total Portion Weight (g) | E28: Serving Size | F28: Recipe Notes
A29: Menu Item 1 | C29: =SUMIFS($F$5:$F$24,$A$5:$A$24,A29) -> 0 | D29: =SUMIFS($G$5:$G$24,$A$5:$A$24,A29) -> 0
A30: Menu Item 2 | C30: =SUMIFS($F$5:$F$24,$A$5:$A$24,A30) -> 0 | D30: =SUMIFS($G$5:$G$24,$A$5:$A$24,A30) -> 0
A31: Menu Item 3 | C31: =SUMIFS($F$5:$F$24,$A$5:$A$24,A31) -> 0 | D31: =SUMIFS($G$5:$G$24,$A$5:$A$24,A31) -> 0
A32: Menu Item 4 | C32: =SUMIFS($F$5:$F$24,$A$5:$A$24,A32) -> 0 | D32: =SUMIFS($G$5:$G$24,$A$5:$A$24,A32) -> 0
A33: Menu Item 5 | C33: =SUMIFS($F$5:$F$24,$A$5:$A$24,A33) -> 0 | D33: =SUMIFS($G$5:$G$24,$A$5:$A$24,A33) -> 0
A34: Menu Item 6 | C34: =SUMIFS($F$5:$F$24,$A$5:$A$24,A34) -> 0 | D34: =SUMIFS($G$5:$G$24,$A$5:$A$24,A34) -> 0

Sheet Packaging
A1: Packaging
A2: Packaging cost per menu item, linked into Menu Pricing.
A4: Menu Item | B4: Container | C4: Box | D4: Bag | E4: Napkin/Cutlery | F4: Sauce Cup | G4: Label | H4: Delivery Packaging | I4: Total Packaging Cost
A5: Menu Item 1 | B5: 0 | C5: 0 | D5: 0 | E5: 0 | F5: 0 | G5: 0 | H5: 0 | I5: =SUM(B5:H5) -> 0
A6: Menu Item 2 | B6: 0 | C6: 0 | D6: 0 | E6: 0 | F6: 0 | G6: 0 | H6: 0 | I6: =SUM(B6:H6) -> 0
A7: Menu Item 3 | B7: 0 | C7: 0 | D7: 0 | E7: 0 | F7: 0 | G7: 0 | H7: 0 | I7: =SUM(B7:H7) -> 0
A8: Menu Item 4 | B8: 0 | C8: 0 | D8: 0 | E8: 0 | F8: 0 | G8: 0 | H8: 0 | I8: =SUM(B8:H8) -> 0
A9: Menu Item 5 | B9: 0 | C9: 0 | D9: 0 | E9: 0 | F9: 0 | G9: 0 | H9: 0 | I9: =SUM(B9:H9) -> 0
A10: Menu Item 6 | B10: 0 | C10: 0 | D10: 0 | E10: 0 | F10: 0 | G10: 0 | H10: 0 | I10: =SUM(B10:H10) -> 0

Sheet Operating Expenses
A1: Operating Expenses
A2: Fixed monthly overhead, allocated down to a cost-per-order figure.
A4: Expense Category | B4: Monthly Amount
A5: Rent | B5: 0
A6: Electricity | B6: 0
A7: Gas | B7: 0
A8: Water | B8: 0
A9: Internet | B9: 0
A10: Insurance | B10: 0
A11: Cleaning | B11: 0
A12: Marketing | B12: 0
A13: Software / POS | B13: 0
A14: Equipment (lease/maint.) | B14: 0
A15: Staff Salaries | B15: 0
A16: Taxes (non-VAT) | B16: 0
... A18: Miscellaneous | B18: 0
A20: Monthly Overhead | B20: =SUM(B5:B18) -> 0
A21: Working Days / Month (from Business Profile) | B21: ='Business Profile'!$B$8 -> 26
A22: Daily Overhead | B22: =IFERROR(B20/B21,0) -> 0
A23: Average Daily Orders (from Business Profile) | B23: ='Business Profile'!$B$14 -> 0
A24: Cost per Order | B24: =IFERROR(B22/B23,0) -> 0
A25: Average Items per Order (from Business Profile) | B25: ='Business Profile'!$B$15 -> 2
A26: Allocated Overhead per Menu Item | B26: =IFERROR(B24/B25,0) -> 0

Sheet Menu Pricing
A1: Menu Pricing
A2: The financial engine: every cost, margin, and pricing recommendation per menu item.
A4: Menu Item | B4: Category | C4: Recipe Cost | D4: Packaging Cost | E4: Labor Cost | F4: Allocated Overhead | G4: Delivery Commission | H4: VAT | I4: Total Cost | J4: Selling Price | K4: Gross Profit | L4: Gross Margin % | M4: Net Profit | N4: Net Margin % | O4: Food Cost % | P4: Markup % | Q4: Break-even Price | R4: Recommended Price | S4: Target Price | T4: Price Gap | U4: Profit Status
A5: Menu Item 1 | C5: =IFERROR(INDEX('Recipe Builder'!$C$29:$C$34,MATCH($A5,'Recipe Builder'!$A$29:$A$34,0)),0) -> 0 | D5: =IFERROR(INDEX(Packaging!$I$5:$I$10,MATCH($A5,Packaging!$A$5:$A$10,0)),0) -> 0 | E5: 0 | F5: =Overhead_Per_Item -> 0 | G5: 0 | H5: =$J5*'Business Profile'!$B$7 -> 0 | I5: =C5+D5+E5+F5+G5 -> 0 | J5: 0 | K5: =J5-C5-D5 -> 0 | L5: =IFERROR(K5/J5,0) -> 0 | M5: =J5-I5 -> 0 | N5: =IFERROR(M5/J5,0) -> 0 | O5: =IFERROR(C5/J5,0) -> 0 | P5: =IFERROR((J5-C5)/C5,0) -> 0 | Q5: =I5 -> 0 | R5: =IFERROR(I5/(1-'Business Profile'!$B$11),0) -> 0 | S5: =IFERROR(C5/'Business Profile'!$B$9,0) -> 0 | T5: =J5-R5 -> 0 | U5: =IF(M5<0,"Losing Money",IF(N5<'Business Profile'!$B$11*0.5,"Low Margin",IF(N5<'Business Profile'!$B$11,"Needs Review",IF(AND(N5>='Business Profile'!$B$11,O5<='Business Profile'!$B$9),"Excellent","Healthy")))) -> Low Margin
A6: Menu Item 2 | C6: =IFERROR(INDEX('Recipe Builder'!$C$29:$C$34,MATCH($A6,'Recipe Builder'!$A$29:$A$34,0)),0) -> 0 | D6: =IFERROR(INDEX(Packaging!$I$5:$I$10,MATCH($A6,Packaging!$A$5:$A$10,0)),0) -> 0 | E6: 0 | F6: =Overhead_Per_Item -> 0 | G6: 0 | H6: =$J6*'Business Profile'!$B$7 -> 0 | I6: =C6+D6+E6+F6+G6 -> 0 | J6: 0 | K6: =J6-C6-D6 -> 0 | L6: =IFERROR(K6/J6,0) -> 0 | M6: =J6-I6 -> 0 | N6: =IFERROR(M6/J6,0) -> 0 | O6: =IFERROR(C6/J6,0) -> 0 | P6: =IFERROR((J6-C6)/C6,0) -> 0 | Q6: =I6 -> 0 | R6: =IFERROR(I6/(1-'Business Profile'!$B$11),0) -> 0 | S6: =IFERROR(C6/'Business Profile'!$B$9,0) -> 0 | T6: =J6-R6 -> 0 | U6: =IF(M6<0,"Losing Money",IF(N6<'Business Profile'!$B$11*0.5,"Low Margin",IF(N6<'Business Profile'!$B$11,"Needs Review",IF(AND(N6>='Business Profile'!$B$11,O6<='Business Profile'!$B$9),"Excellent","Healthy")))) -> Low Margin
A7: Menu Item 3 | C7: =IFERROR(INDEX('Recipe Builder'!$C$29:$C$34,MATCH($A7,'Recipe Builder'!$A$29:$A$34,0)),0) -> 0 | D7: =IFERROR(INDEX(Packaging!$I$5:$I$10,MATCH($A7,Packaging!$A$5:$A$10,0)),0) -> 0 | E7: 0 | F7: =Overhead_Per_Item -> 0 | G7: 0 | H7: =$J7*'Business Profile'!$B$7 -> 0 | I7: =C7+D7+E7+F7+G7 -> 0 | J7: 0 | K7: =J7-C7-D7 -> 0 | L7: =IFERROR(K7/J7,0) -> 0 | M7: =J7-I7 -> 0 | N7: =IFERROR(M7/J7,0) -> 0 | O7: =IFERROR(C7/J7,0) -> 0 | P7: =IFERROR((J7-C7)/C7,0) -> 0 | Q7: =I7 -> 0 | R7: =IFERROR(I7/(1-'Business Profile'!$B$11),0) -> 0 | S7: =IFERROR(C7/'Business Profile'!$B$9,0) -> 0 | T7: =J7-R7 -> 0 | U7: =IF(M7<0,"Losing Money",IF(N7<'Business Profile'!$B$11*0.5,"Low Margin",IF(N7<'Business Profile'!$B$11,"Needs Review",IF(AND(N7>='Business Profile'!$B$11,O7<='Business Profile'!$B$9),"Excellent","Healthy")))) -> Low Margin
A8: Menu Item 4 | C8: =IFERROR(INDEX('Recipe Builder'!$C$29:$C$34,MATCH($A8,'Recipe Builder'!$A$29:$A$34,0)),0) -> 0 | D8: =IFERROR(INDEX(Packaging!$I$5:$I$10,MATCH($A8,Packaging!$A$5:$A$10,0)),0) -> 0 | E8: 0 | F8: =Overhead_Per_Item -> 0 | G8: 0 | H8: =$J8*'Business Profile'!$B$7 -> 0 | I8: =C8+D8+E8+F8+G8 -> 0 | J8: 0 | K8: =J8-C8-D8 -> 0 | L8: =IFERROR(K8/J8,0) -> 0 | M8: =J8-I8 -> 0 | N8: =IFERROR(M8/J8,0) -> 0 | O8: =IFERROR(C8/J8,0) -> 0 | P8: =IFERROR((J8-C8)/C8,0) -> 0 | Q8: =I8 -> 0 | R8: =IFERROR(I8/(1-'Business Profile'!$B$11),0) -> 0 | S8: =IFERROR(C8/'Business Profile'!$B$9,0) -> 0 | T8: =J8-R8 -> 0 | U8: =IF(M8<0,"Losing Money",IF(N8<'Business Profile'!$B$11*0.5,"Low Margin",IF(N8<'Business Profile'!$B$11,"Needs Review",IF(AND(N8>='Business Profile'!$B$11,O8<='Business Profile'!$B$9),"Excellent","Healthy")))) -> Low Margin
A9: Menu Item 5 | C9: =IFERROR(INDEX('Recipe Builder'!$C$29:$C$34,MATCH($A9,'Recipe Builder'!$A$29:$A$34,0)),0) -> 0 | D9: =IFERROR(INDEX(Packaging!$I$5:$I$10,MATCH($A9,Packaging!$A$5:$A$10,0)),0) -> 0 | E9: 0 | F9: =Overhead_Per_Item -> 0 | G9: 0 | H9: =$J9*'Business Profile'!$B$7 -> 0 | I9: =C9+D9+E9+F9+G9 -> 0 | J9: 0 | K9: =J9-C9-D9 -> 0 | L9: =IFERROR(K9/J9,0) -> 0 | M9: =J9-I9 -> 0 | N9: =IFERROR(M9/J9,0) -> 0 | O9: =IFERROR(C9/J9,0) -> 0 | P9: =IFERROR((J9-C9)/C9,0) -> 0 | Q9: =I9 -> 0 | R9: =IFERROR(I9/(1-'Business Profile'!$B$11),0) -> 0 | S9: =IFERROR(C9/'Business Profile'!$B$9,0) -> 0 | T9: =J9-R9 -> 0 | U9: =IF(M9<0,"Losing Money",IF(N9<'Business Profile'!$B$11*0.5,"Low Margin",IF(N9<'Business Profile'!$B$11,"Needs Review",IF(AND(N9>='Business Profile'!$B$11,O9<='Business Profile'!$B$9),"Excellent","Healthy")))) -> Low Margin
A10: Menu Item 6 | C10: =IFERROR(INDEX('Recipe Builder'!$C$29:$C$34,MATCH($A10,'Recipe Builder'!$A$29:$A$34,0)),0) -> 0 | D10: =IFERROR(INDEX(Packaging!$I$5:$I$10,MATCH($A10,Packaging!$A$5:$A$10,0)),0) -> 0 | E10: 0 | F10: =Overhead_Per_Item -> 0 | G10: 0 | H10: =$J10*'Business Profile'!$B$7 -> 0 | I10: =C10+D10+E10+F10+G10 -> 0 | J10: 0 | K10: =J10-C10-D10 -> 0 | L10: =IFERROR(K10/J10,0) -> 0 | M10: =J10-I10 -> 0 | N10: =IFERROR(M10/J10,0) -> 0 | O10: =IFERROR(C10/J10,0) -> 0 | P10: =IFERROR((J10-C10)/C10,0) -> 0 | Q10: =I10 -> 0 | R10: =IFERROR(I10/(1-'Business Profile'!$B$11),0) -> 0 | S10: =IFERROR(C10/'Business Profile'!$B$9,0) -> 0 | T10: =J10-R10 -> 0 | U10: =IF(M10<0,"Losing Money",IF(N10<'Business Profile'!$B$11*0.5,"Low Margin",IF(N10<'Business Profile'!$B$11,"Needs Review",IF(AND(N10>='Business Profile'!$B$11,O10<='Business Profile'!$B$9),"Excellent","Healthy")))) -> Low Margin

Sheet Sales
A1: Sales
A2: Daily sales log. Paste from your POS export — revenue and profit calculate automatically.
A4: Date | B4: Menu Item | C4: Quantity | D4: Revenue | E4: Gross Profit | F4: Net Profit
A5: 46023 | B5: Menu Item 1 | C5: 0 | D5: =IFERROR(C5*INDEX('Menu Pricing'!$J$5:$J$10,MATCH(B5,'Menu Pricing'!$A$5:$A$10,0)),0) -> 0 | E5: =IFERROR(C5*INDEX('Menu Pricing'!$K$5:$K$10,MATCH(B5,'Menu Pricing'!$A$5:$A$10,0)),0) -> 0 | F5: =IFERROR(C5*INDEX('Menu Pricing'!$M$5:$M$10,MATCH(B5,'Menu Pricing'!$A$5:$A$10,0)),0) -> 0
A6: 46023 | B6: Menu Item 2 | C6: 0 | D6: =IFERROR(C6*INDEX('Menu Pricing'!$J$5:$J$10,MATCH(B6,'Menu Pricing'!$A$5:$A$10,0)),0) -> 0 | E6: =IFERROR(C6*INDEX('Menu Pricing'!$K$5:$K$10,MATCH(B6,'Menu Pricing'!$A$5:$A$10,0)),0) -> 0 | F6: =IFERROR(C6*INDEX('Menu Pricing'!$M$5:$M$10,MATCH(B6,'Menu Pricing'!$A$5:$A$10,0)),0) -> 0
A7: 46023 | B7: Menu Item 3 | C7: 0 | D7: =IFERROR(C7*INDEX('Menu Pricing'!$J$5:$J$10,MATCH(B7,'Menu Pricing'!$A$5:$A$10,0)),0) -> 0 | E7: =IFERROR(C7*INDEX('Menu Pricing'!$K$5:$K$10,MATCH(B7,'Menu Pricing'!$A$5:$A$10,0)),0) -> 0 | F7: =IFERROR(C7*INDEX('Menu Pricing'!$M$5:$M$10,MATCH(B7,'Menu Pricing'!$A$5:$A$10,0)),0) -> 0
A8: 46023 | B8: Menu Item 4 | C8: 0 | D8: =IFERROR(C8*INDEX('Menu Pricing'!$J$5:$J$10,MATCH(B8,'Menu Pricing'!$A$5:$A$10,0)),0) -> 0 | E8: =IFERROR(C8*INDEX('Menu Pricing'!$K$5:$K$10,MATCH(B8,'Menu Pricing'!$A$5:$A$10,0)),0) -> 0 | F8: =IFERROR(C8*INDEX('Menu Pricing'!$M$5:$M$10,MATCH(B8,'Menu Pricing'!$A$5:$A$10,0)),0) -> 0
A9: 46023 | B9: Menu Item 5 | C9: 0 | D9: =IFERROR(C9*INDEX('Menu Pricing'!$J$5:$J$10,MATCH(B9,'Menu Pricing'!$A$5:$A$10,0)),0) -> 0 | E9: =IFERROR(C9*INDEX('Menu Pricing'!$K$5:$K$10,MATCH(B9,'Menu Pricing'!$A$5:$A$10,0)),0) -> 0 | F9: =IFERROR(C9*INDEX('Menu Pricing'!$M$5:$M$10,MATCH(B9,'Menu Pricing'!$A$5:$A$10,0)),0) -> 0
A10: 46023 | B10: Menu Item 6 | C10: 0 | D10: =IFERROR(C10*INDEX('Menu Pricing'!$J$5:$J$10,MATCH(B10,'Menu Pricing'!$A$5:$A$10,0)),0) -> 0 | E10: =IFERROR(C10*INDEX('Menu Pricing'!$K$5:$K$10,MATCH(B10,'Menu Pricing'!$A$5:$A$10,0)),0) -> 0 | F10: =IFERROR(C10*INDEX('Menu Pricing'!$M$5:$M$10,MATCH(B10,'Menu Pricing'!$A$5:$A$10,0)),0) -> 0
A11: 46024 | B11: Menu Item 1 | C11: 0 | D11: =IFERROR(C11*INDEX('Menu Pricing'!$J$5:$J$10,MATCH(B11,'Menu Pricing'!$A$5:$A$10,0)),0) -> 0 | E11: =IFERROR(C11*INDEX('Menu Pricing'!$K$5:$K$10,MATCH(B11,'Menu Pricing'!$A$5:$A$10,0)),0) -> 0 | F11: =IFERROR(C11*INDEX('Menu Pricing'!$M$5:$M$10,MATCH(B11,'Menu Pricing'!$A$5:$A$10,0)),0) -> 0
A12: 46024 | B12: Menu Item 2 | C12: 0 | D12: =IFERROR(C12*INDEX('Menu Pricing'!$J$5:$J$10,MATCH(B12,'Menu Pricing'!$A$5:$A$10,0)),0) -> 0 | E12: =IFERROR(C12*INDEX('Menu Pricing'!$K$5:$K$10,MATCH(B12,'Menu Pricing'!$A$5:$A$10,0)),0) -> 0 | F12: =IFERROR(C12*INDEX('Menu Pricing'!$M$5:$M$10,MATCH(B12,'Menu Pricing'!$A$5:$A$10,0)),0) -> 0
A13: 46024 | B13: Menu Item 3 | C13: 0 | D13: =IFERROR(C13*INDEX('Menu Pricing'!$J$5:$J$10,MATCH(B13,'Menu Pricing'!$A$5:$A$10,0)),0) -> 0 | E13: =IFERROR(C13*INDEX('Menu Pricing'!$K$5:$K$10,MATCH(B13,'Menu Pricing'!$A$5:$A$10,0)),0) -> 0 | F13: =IFERROR(C13*INDEX('Menu Pricing'!$M$5:$M$10,MATCH(B13,'Menu Pricing'!$A$5:$A$10,0)),0) -> 0
A14: 46024 | B14: Menu Item 4 | C14: 0 | D14: =IFERROR(C14*INDEX('Menu Pricing'!$J$5:$J$10,MATCH(B14,'Menu Pricing'!$A$5:$A$10,0)),0) -> 0 | E14: =IFERROR(C14*INDEX('Menu Pricing'!$K$5:$K$10,MATCH(B14,'Menu Pricing'!$A$5:$A$10,0)),0) -> 0 | F14: =IFERROR(C14*INDEX('Menu Pricing'!$M$5:$M$10,MATCH(B14,'Menu Pricing'!$A$5:$A$10,0)),0) -> 0
A15: 46024 | B15: Menu Item 5 | C15: 0 | D15: =IFERROR(C15*INDEX('Menu Pricing'!$J$5:$J$10,MATCH(B15,'Menu Pricing'!$A$5:$A$10,0)),0) -> 0 | E15: =IFERROR(C15*INDEX('Menu Pricing'!$K$5:$K$10,MATCH(B15,'Menu Pricing'!$A$5:$A$10,0)),0) -> 0 | F15: =IFERROR(C15*INDEX('Menu Pricing'!$M$5:$M$10,MATCH(B15,'Menu Pricing'!$A$5:$A$10,0)),0) -> 0
A16: 46024 | B16: Menu Item 6 | C16: 0 | D16: =IFERROR(C16*INDEX('Menu Pricing'!$J$5:$J$10,MATCH(B16,'Menu Pricing'!$A$5:$A$10,0)),0) -> 0 | E16: =IFERROR(C16*INDEX('Menu Pricing'!$K$5:$K$10,MATCH(B16,'Menu Pricing'!$A$5:$A$10,0)),0) -> 0 | F16: =IFERROR(C16*INDEX('Menu Pricing'!$M$5:$M$10,MATCH(B16,'Menu Pricing'!$A$5:$A$10,0)),0) -> 0
... A124: 46042 | B124: Menu Item 6 | C124: 0 | D124: =IFERROR(C124*INDEX('Menu Pricing'!$J$5:$J$10,MATCH(B124,'Menu Pricing'!$A$5:$A$10,0)),0) -> 0 | E124: =IFERROR(C124*INDEX('Menu Pricing'!$K$5:$K$10,MATCH(B124,'Menu Pricing'!$A$5:$A$10,0)),0) -> 0 | F124: =IFERROR(C124*INDEX('Menu Pricing'!$M$5:$M$10,MATCH(B124,'Menu Pricing'!$A$5:$A$10,0)),0) -> 0

Sheet Inventory Summary
A1: Inventory Summary
A2: Stock position and reorder alerts, pulled from Ingredients Database.
A4: Ingredient | B4: Current Stock | C4: Minimum Stock | D4: Reorder Needed | E4: Supplier | F4: Estimated Inventory Value
A5: ='Ingredients Database'!A5 -> Ingredient 1 | B5: ='Ingredients Database'!I5 -> 0 | C5: ='Ingredients Database'!J5 -> 0 | D5: =IF(B5<C5,"Reorder Now","OK") -> OK | E5: ='Ingredients Database'!C5 -> 0 | F5: =B5*'Ingredients Database'!F5 -> 0
A6: ='Ingredients Database'!A6 -> Ingredient 2 | B6: ='Ingredients Database'!I6 -> 0 | C6: ='Ingredients Database'!J6 -> 0 | D6: =IF(B6<C6,"Reorder Now","OK") -> OK | E6: ='Ingredients Database'!C6 -> 0 | F6: =B6*'Ingredients Database'!F6 -> 0
A7: ='Ingredients Database'!A7 -> Ingredient 3 | B7: ='Ingredients Database'!I7 -> 0 | C7: ='Ingredients Database'!J7 -> 0 | D7: =IF(B7<C7,"Reorder Now","OK") -> OK | E7: ='Ingredients Database'!C7 -> 0 | F7: =B7*'Ingredients Database'!F7 -> 0
A8: ='Ingredients Database'!A8 -> Ingredient 4 | B8: ='Ingredients Database'!I8 -> 0 | C8: ='Ingredients Database'!J8 -> 0 | D8: =IF(B8<C8,"Reorder Now","OK") -> OK | E8: ='Ingredients Database'!C8 -> 0 | F8: =B8*'Ingredients Database'!F8 -> 0
A9: ='Ingredients Database'!A9 -> Ingredient 5 | B9: ='Ingredients Database'!I9 -> 0 | C9: ='Ingredients Database'!J9 -> 0 | D9: =IF(B9<C9,"Reorder Now","OK") -> OK | E9: ='Ingredients Database'!C9 -> 0 | F9: =B9*'Ingredients Database'!F9 -> 0
A10: ='Ingredients Database'!A10 -> Ingredient 6 | B10: ='Ingredients Database'!I10 -> 0 | C10: ='Ingredients Database'!J10 -> 0 | D10: =IF(B10<C10,"Reorder Now","OK") -> OK | E10: ='Ingredients Database'!C10 -> 0 | F10: =B10*'Ingredients Database'!F10 -> 0
A11: ='Ingredients Database'!A11 -> Ingredient 7 | B11: ='Ingredients Database'!I11 -> 0 | C11: ='Ingredients Database'!J11 -> 0 | D11: =IF(B11<C11,"Reorder Now","OK") -> OK | E11: ='Ingredients Database'!C11 -> 0 | F11: =B11*'Ingredients Database'!F11 -> 0
A12: ='Ingredients Database'!A12 -> Ingredient 8 | B12: ='Ingredients Database'!I12 -> 0 | C12: ='Ingredients Database'!J12 -> 0 | D12: =IF(B12<C12,"Reorder Now","OK") -> OK | E12: ='Ingredients Database'!C12 -> 0 | F12: =B12*'Ingredients Database'!F12 -> 0
A13: ='Ingredients Database'!A13 -> Ingredient 9 | B13: ='Ingredients Database'!I13 -> 0 | C13: ='Ingredients Database'!J13 -> 0 | D13: =IF(B13<C13,"Reorder Now","OK") -> OK | E13: ='Ingredients Database'!C13 -> 0 | F13: =B13*'Ingredients Database'!F13 -> 0
A14: ='Ingredients Database'!A14 -> Ingredient 10 | B14: ='Ingredients Database'!I14 -> 0 | C14: ='Ingredients Database'!J14 -> 0 | D14: =IF(B14<C14,"Reorder Now","OK") -> OK | E14: ='Ingredients Database'!C14 -> 0 | F14: =B14*'Ingredients Database'!F14 -> 0
A15: ='Ingredients Database'!A15 -> Ingredient 11 | B15: ='Ingredients Database'!I15 -> 0 | C15: ='Ingredients Database'!J15 -> 0 | D15: =IF(B15<C15,"Reorder Now","OK") -> OK | E15: ='Ingredients Database'!C15 -> 0 | F15: =B15*'Ingredients Database'!F15 -> 0
A16: ='Ingredients Database'!A16 -> Ingredient 12 | B16: ='Ingredients Database'!I16 -> 0 | C16: ='Ingredients Database'!J16 -> 0 | D16: =IF(B16<C16,"Reorder Now","OK") -> OK | E16: ='Ingredients Database'!C16 -> 0 | F16: =B16*'Ingredients Database'!F16 -> 0

Sheet Menu Engineering
A1: Menu Engineering
A2: Classic Star / Plow Horse / Puzzle / Dog matrix, based on actual sales volume and margin.
A4: Menu Item | B4: Units Sold (period) | C4: Gross Margin % | D4: Avg Units Sold | E4: Avg Gross Margin % | F4: Classification | G4: Recommendation
A5: ='Menu Pricing'!A5 -> Menu Item 1 | B5: =SUMIFS(Sales!$C$5:$C$124,Sales!$B$5:$B$124,A5) -> 0 | C5: ='Menu Pricing'!L5 -> 0 | D5: =AVERAGE(B5:B10) -> 0 | E5: =AVERAGE(C5:C10) -> 0 | F5: =IF(AND(B5>=D5,C5>=E5),"⭐ Star",IF(AND(B5>=D5,C5<E5),"🐎 Plow Horse",IF(AND(B5<D5,C5>=E5),"🧩 Puzzle","🐶 Dog"))) -> ⭐ Star | G5: =IF(F5="⭐ Star","Protect quality & keep visible on the menu",IF(F5="🐎 Plow Horse","Popular but thin margin — raise price slightly or cut portion cost",IF(F5="🧩 Puzzle","Profitable but under-ordered — promote or reposition on menu","Low popularity & low profit — consider removing or relaunching"))) -> Protect quality & keep visible on the menu
A6: ='Menu Pricing'!A6 -> Menu Item 2 | B6: =SUMIFS(Sales!$C$5:$C$124,Sales!$B$5:$B$124,A6) -> 0 | C6: ='Menu Pricing'!L6 -> 0 | D6: =AVERAGE(B5:B10) -> 0 | E6: =AVERAGE(C5:C10) -> 0 | F6: =IF(AND(B6>=D6,C6>=E6),"⭐ Star",IF(AND(B6>=D6,C6<E6),"🐎 Plow Horse",IF(AND(B6<D6,C6>=E6),"🧩 Puzzle","🐶 Dog"))) -> ⭐ Star | G6: =IF(F6="⭐ Star","Protect quality & keep visible on the menu",IF(F6="🐎 Plow Horse","Popular but thin margin — raise price slightly or cut portion cost",IF(F6="🧩 Puzzle","Profitable but under-ordered — promote or reposition on menu","Low popularity & low profit — consider removing or relaunching"))) -> Protect quality & keep visible on the menu
A7: ='Menu Pricing'!A7 -> Menu Item 3 | B7: =SUMIFS(Sales!$C$5:$C$124,Sales!$B$5:$B$124,A7) -> 0 | C7: ='Menu Pricing'!L7 -> 0 | D7: =AVERAGE(B5:B10) -> 0 | E7: =AVERAGE(C5:C10) -> 0 | F7: =IF(AND(B7>=D7,C7>=E7),"⭐ Star",IF(AND(B7>=D7,C7<E7),"🐎 Plow Horse",IF(AND(B7<D7,C7>=E7),"🧩 Puzzle","🐶 Dog"))) -> ⭐ Star | G7: =IF(F7="⭐ Star","Protect quality & keep visible on the menu",IF(F7="🐎 Plow Horse","Popular but thin margin — raise price slightly or cut portion cost",IF(F7="🧩 Puzzle","Profitable but under-ordered — promote or reposition on menu","Low popularity & low profit — consider removing or relaunching"))) -> Protect quality & keep visible on the menu
A8: ='Menu Pricing'!A8 -> Menu Item 4 | B8: =SUMIFS(Sales!$C$5:$C$124,Sales!$B$5:$B$124,A8) -> 0 | C8: ='Menu Pricing'!L8 -> 0 | D8: =AVERAGE(B5:B10) -> 0 | E8: =AVERAGE(C5:C10) -> 0 | F8: =IF(AND(B8>=D8,C8>=E8),"⭐ Star",IF(AND(B8>=D8,C8<E8),"🐎 Plow Horse",IF(AND(B8<D8,C8>=E8),"🧩 Puzzle","🐶 Dog"))) -> ⭐ Star | G8: =IF(F8="⭐ Star","Protect quality & keep visible on the menu",IF(F8="🐎 Plow Horse","Popular but thin margin — raise price slightly or cut portion cost",IF(F8="🧩 Puzzle","Profitable but under-ordered — promote or reposition on menu","Low popularity & low profit — consider removing or relaunching"))) -> Protect quality & keep visible on the menu
A9: ='Menu Pricing'!A9 -> Menu Item 5 | B9: =SUMIFS(Sales!$C$5:$C$124,Sales!$B$5:$B$124,A9) -> 0 | C9: ='Menu Pricing'!L9 -> 0 | D9: =AVERAGE(B5:B10) -> 0 | E9: =AVERAGE(C5:C10) -> 0 | F9: =IF(AND(B9>=D9,C9>=E9),"⭐ Star",IF(AND(B9>=D9,C9<E9),"🐎 Plow Horse",IF(AND(B9<D9,C9>=E9),"🧩 Puzzle","🐶 Dog"))) -> ⭐ Star | G9: =IF(F9="⭐ Star","Protect quality & keep visible on the menu",IF(F9="🐎 Plow Horse","Popular but thin margin — raise price slightly or cut portion cost",IF(F9="🧩 Puzzle","Profitable but under-ordered — promote or reposition on menu","Low popularity & low profit — consider removing or relaunching"))) -> Protect quality & keep visible on the menu
A10: ='Menu Pricing'!A10 -> Menu Item 6 | B10: =SUMIFS(Sales!$C$5:$C$124,Sales!$B$5:$B$124,A10) -> 0 | C10: ='Menu Pricing'!L10 -> 0 | D10: =AVERAGE(B5:B10) -> 0 | E10: =AVERAGE(C5:C10) -> 0 | F10: =IF(AND(B10>=D10,C10>=E10),"⭐ Star",IF(AND(B10>=D10,C10<E10),"🐎 Plow Horse",IF(AND(B10<D10,C10>=E10),"🧩 Puzzle","🐶 Dog"))) -> ⭐ Star | G10: =IF(F10="⭐ Star","Protect quality & keep visible on the menu",IF(F10="🐎 Plow Horse","Popular but thin margin — raise price slightly or cut portion cost",IF(F10="🧩 Puzzle","Profitable but under-ordered — promote or reposition on menu","Low popularity & low profit — consider removing or relaunching"))) -> Protect quality & keep visible on the menu

Sheet Profit Leakage
A1: Profit Leakage
A2: Where money is actually being lost, item by item, estimated in dollars per month.
A4: Menu Item | B4: Leak Type | C4: Detail | D4: Gap per Unit | E4: Monthly Units Sold (proj.) | F4: Estimated Monthly Loss
A5: ='Menu Pricing'!A5 -> Menu Item 1 | B5: =IF('Menu Pricing'!O5>'Business Profile'!$B$9,"High Food Cost",IF('Menu Pricing'!T5<0,"Underpriced vs. Recommended",IF('Menu Pricing'!U5="Losing Money","Selling Below Total Cost","None"))) -> None | C5: =IF(B5="High Food Cost","Food cost "&TEXT('Menu Pricing'!O5,"0.0%")&" vs target "&TEXT('Business Profile'!$B$9,"0.0%"),IF(B5="Underpriced vs. Recommended","Priced "&TEXT(-'Menu Pricing'!T5,"$0.00")&" below recommended price",IF(B5="Selling Below Total Cost","Selling price does not cover total cost per unit","No leak detected"))) -> No leak detected | D5: =MAX(0,-'Menu Pricing'!T5) -> 0 | E5: =IFERROR(SUMIFS(Sales!$C$5:$C$124,Sales!$B$5:$B$124,A5)/((Sales!$A$124-Sales!$A$5+1)/'Business Profile'!$B$8*'Business Profile'!$B$8) * 'Business Profile'!$B$8,0) -> 0 | F5: =D5*E5 -> 0
A6: ='Menu Pricing'!A6 -> Menu Item 2 | B6: =IF('Menu Pricing'!O6>'Business Profile'!$B$9,"High Food Cost",IF('Menu Pricing'!T6<0,"Underpriced vs. Recommended",IF('Menu Pricing'!U6="Losing Money","Selling Below Total Cost","None"))) -> None | C6: =IF(B6="High Food Cost","Food cost "&TEXT('Menu Pricing'!O6,"0.0%")&" vs target "&TEXT('Business Profile'!$B$9,"0.0%"),IF(B6="Underpriced vs. Recommended","Priced "&TEXT(-'Menu Pricing'!T6,"$0.00")&" below recommended price",IF(B6="Selling Below Total Cost","Selling price does not cover total cost per unit","No leak detected"))) -> No leak detected | D6: =MAX(0,-'Menu Pricing'!T6) -> 0 | E6: =IFERROR(SUMIFS(Sales!$C$5:$C$124,Sales!$B$5:$B$124,A6)/((Sales!$A$124-Sales!$A$5+1)/'Business Profile'!$B$8*'Business Profile'!$B$8) * 'Business Profile'!$B$8,0) -> 0 | F6: =D6*E6 -> 0
A7: ='Menu Pricing'!A7 -> Menu Item 3 | B7: =IF('Menu Pricing'!O7>'Business Profile'!$B$9,"High Food Cost",IF('Menu Pricing'!T7<0,"Underpriced vs. Recommended",IF('Menu Pricing'!U7="Losing Money","Selling Below Total Cost","None"))) -> None | C7: =IF(B7="High Food Cost","Food cost "&TEXT('Menu Pricing'!O7,"0.0%")&" vs target "&TEXT('Business Profile'!$B$9,"0.0%"),IF(B7="Underpriced vs. Recommended","Priced "&TEXT(-'Menu Pricing'!T7,"$0.00")&" below recommended price",IF(B7="Selling Below Total Cost","Selling price does not cover total cost per unit","No leak detected"))) -> No leak detected | D7: =MAX(0,-'Menu Pricing'!T7) -> 0 | E7: =IFERROR(SUMIFS(Sales!$C$5:$C$124,Sales!$B$5:$B$124,A7)/((Sales!$A$124-Sales!$A$5+1)/'Business Profile'!$B$8*'Business Profile'!$B$8) * 'Business Profile'!$B$8,0) -> 0 | F7: =D7*E7 -> 0
A8: ='Menu Pricing'!A8 -> Menu Item 4 | B8: =IF('Menu Pricing'!O8>'Business Profile'!$B$9,"High Food Cost",IF('Menu Pricing'!T8<0,"Underpriced vs. Recommended",IF('Menu Pricing'!U8="Losing Money","Selling Below Total Cost","None"))) -> None | C8: =IF(B8="High Food Cost","Food cost "&TEXT('Menu Pricing'!O8,"0.0%")&" vs target "&TEXT('Business Profile'!$B$9,"0.0%"),IF(B8="Underpriced vs. Recommended","Priced "&TEXT(-'Menu Pricing'!T8,"$0.00")&" below recommended price",IF(B8="Selling Below Total Cost","Selling price does not cover total cost per unit","No leak detected"))) -> No leak detected | D8: =MAX(0,-'Menu Pricing'!T8) -> 0 | E8: =IFERROR(SUMIFS(Sales!$C$5:$C$124,Sales!$B$5:$B$124,A8)/((Sales!$A$124-Sales!$A$5+1)/'Business Profile'!$B$8*'Business Profile'!$B$8) * 'Business Profile'!$B$8,0) -> 0 | F8: =D8*E8 -> 0
A9: ='Menu Pricing'!A9 -> Menu Item 5 | B9: =IF('Menu Pricing'!O9>'Business Profile'!$B$9,"High Food Cost",IF('Menu Pricing'!T9<0,"Underpriced vs. Recommended",IF('Menu Pricing'!U9="Losing Money","Selling Below Total Cost","None"))) -> None | C9: =IF(B9="High Food Cost","Food cost "&TEXT('Menu Pricing'!O9,"0.0%")&" vs target "&TEXT('Business Profile'!$B$9,"0.0%"),IF(B9="Underpriced vs. Recommended","Priced "&TEXT(-'Menu Pricing'!T9,"$0.00")&" below recommended price",IF(B9="Selling Below Total Cost","Selling price does not cover total cost per unit","No leak detected"))) -> No leak detected | D9: =MAX(0,-'Menu Pricing'!T9) -> 0 | E9: =IFERROR(SUMIFS(Sales!$C$5:$C$124,Sales!$B$5:$B$124,A9)/((Sales!$A$124-Sales!$A$5+1)/'Business Profile'!$B$8*'Business Profile'!$B$8) * 'Business Profile'!$B$8,0) -> 0 | F9: =D9*E9 -> 0
A10: ='Menu Pricing'!A10 -> Menu Item 6 | B10: =IF('Menu Pricing'!O10>'Business Profile'!$B$9,"High Food Cost",IF('Menu Pricing'!T10<0,"Underpriced vs. Recommended",IF('Menu Pricing'!U10="Losing Money","Selling Below Total Cost","None"))) -> None | C10: =IF(B10="High Food Cost","Food cost "&TEXT('Menu Pricing'!O10,"0.0%")&" vs target "&TEXT('Business Profile'!$B$9,"0.0%"),IF(B10="Underpriced vs. Recommended","Priced "&TEXT(-'Menu Pricing'!T10,"$0.00")&" below recommended price",IF(B10="Selling Below Total Cost","Selling price does not cover total cost per unit","No leak detected"))) -> No leak detected | D10: =MAX(0,-'Menu Pricing'!T10) -> 0 | E10: =IFERROR(SUMIFS(Sales!$C$5:$C$124,Sales!$B$5:$B$124,A10)/((Sales!$A$124-Sales!$A$5+1)/'Business Profile'!$B$8*'Business Profile'!$B$8) * 'Business Profile'!$B$8,0) -> 0 | F10: =D10*E10 -> 0
A12: Total Estimated Monthly Profit Leakage | F12: =SUM(F5:F10) -> 0

Sheet Recommendations
A1: Recommendations
A2: Automatically generated, prioritized actions based on the rest of the workbook.
A4: Priority | B4: Menu Item | C4: Recommendation | D4: Estimated Impact
A5: =IF('Menu Pricing'!U5="Losing Money",1,IF('Menu Pricing'!U5="Low Margin",2,IF('Menu Pricing'!U5="Needs Review",3,4))) -> 2 | B5: ='Menu Pricing'!A5 -> Menu Item 1 | C5: =IF('Menu Pricing'!U5="Losing Money","Raise price to at least "&TEXT('Menu Pricing'!R5,"$0.00")&" or cut recipe/packaging cost — currently sold below total cost",IF('Menu Pricing'!U5="Low Margin","Increase price toward "&TEXT('Menu Pricing'!R5,"$0.00")&" or reduce ingredient cost to hit target margin",IF('Menu Pricing'!U5="Needs Review","Review pricing — close to target but not yet there","Performing well — protect quality and keep promoting"))) -> Increase price toward $0.00 or reduce ingredient cost to hit target margin | D5: =MAX(0,'Menu Pricing'!R5-'Menu Pricing'!J5)*SUMIFS(Sales!$C$5:$C$124,Sales!$B$5:$B$124,B5) -> 0
A6: =IF('Menu Pricing'!U6="Losing Money",1,IF('Menu Pricing'!U6="Low Margin",2,IF('Menu Pricing'!U6="Needs Review",3,4))) -> 2 | B6: ='Menu Pricing'!A6 -> Menu Item 2 | C6: =IF('Menu Pricing'!U6="Losing Money","Raise price to at least "&TEXT('Menu Pricing'!R6,"$0.00")&" or cut recipe/packaging cost — currently sold below total cost",IF('Menu Pricing'!U6="Low Margin","Increase price toward "&TEXT('Menu Pricing'!R6,"$0.00")&" or reduce ingredient cost to hit target margin",IF('Menu Pricing'!U6="Needs Review","Review pricing — close to target but not yet there","Performing well — protect quality and keep promoting"))) -> Increase price toward $0.00 or reduce ingredient cost to hit target margin | D6: =MAX(0,'Menu Pricing'!R6-'Menu Pricing'!J6)*SUMIFS(Sales!$C$5:$C$124,Sales!$B$5:$B$124,B6) -> 0
A7: =IF('Menu Pricing'!U7="Losing Money",1,IF('Menu Pricing'!U7="Low Margin",2,IF('Menu Pricing'!U7="Needs Review",3,4))) -> 2 | B7: ='Menu Pricing'!A7 -> Menu Item 3 | C7: =IF('Menu Pricing'!U7="Losing Money","Raise price to at least "&TEXT('Menu Pricing'!R7,"$0.00")&" or cut recipe/packaging cost — currently sold below total cost",IF('Menu Pricing'!U7="Low Margin","Increase price toward "&TEXT('Menu Pricing'!R7,"$0.00")&" or reduce ingredient cost to hit target margin",IF('Menu Pricing'!U7="Needs Review","Review pricing — close to target but not yet there","Performing well — protect quality and keep promoting"))) -> Increase price toward $0.00 or reduce ingredient cost to hit target margin | D7: =MAX(0,'Menu Pricing'!R7-'Menu Pricing'!J7)*SUMIFS(Sales!$C$5:$C$124,Sales!$B$5:$B$124,B7) -> 0
A8: =IF('Menu Pricing'!U8="Losing Money",1,IF('Menu Pricing'!U8="Low Margin",2,IF('Menu Pricing'!U8="Needs Review",3,4))) -> 2 | B8: ='Menu Pricing'!A8 -> Menu Item 4 | C8: =IF('Menu Pricing'!U8="Losing Money","Raise price to at least "&TEXT('Menu Pricing'!R8,"$0.00")&" or cut recipe/packaging cost — currently sold below total cost",IF('Menu Pricing'!U8="Low Margin","Increase price toward "&TEXT('Menu Pricing'!R8,"$0.00")&" or reduce ingredient cost to hit target margin",IF('Menu Pricing'!U8="Needs Review","Review pricing — close to target but not yet there","Performing well — protect quality and keep promoting"))) -> Increase price toward $0.00 or reduce ingredient cost to hit target margin | D8: =MAX(0,'Menu Pricing'!R8-'Menu Pricing'!J8)*SUMIFS(Sales!$C$5:$C$124,Sales!$B$5:$B$124,B8) -> 0
A9: =IF('Menu Pricing'!U9="Losing Money",1,IF('Menu Pricing'!U9="Low Margin",2,IF('Menu Pricing'!U9="Needs Review",3,4))) -> 2 | B9: ='Menu Pricing'!A9 -> Menu Item 5 | C9: =IF('Menu Pricing'!U9="Losing Money","Raise price to at least "&TEXT('Menu Pricing'!R9,"$0.00")&" or cut recipe/packaging cost — currently sold below total cost",IF('Menu Pricing'!U9="Low Margin","Increase price toward "&TEXT('Menu Pricing'!R9,"$0.00")&" or reduce ingredient cost to hit target margin",IF('Menu Pricing'!U9="Needs Review","Review pricing — close to target but not yet there","Performing well — protect quality and keep promoting"))) -> Increase price toward $0.00 or reduce ingredient cost to hit target margin | D9: =MAX(0,'Menu Pricing'!R9-'Menu Pricing'!J9)*SUMIFS(Sales!$C$5:$C$124,Sales!$B$5:$B$124,B9) -> 0
A10: =IF('Menu Pricing'!U10="Losing Money",1,IF('Menu Pricing'!U10="Low Margin",2,IF('Menu Pricing'!U10="Needs Review",3,4))) -> 2 | B10: ='Menu Pricing'!A10 -> Menu Item 6 | C10: =IF('Menu Pricing'!U10="Losing Money","Raise price to at least "&TEXT('Menu Pricing'!R10,"$0.00")&" or cut recipe/packaging cost — currently sold below total cost",IF('Menu Pricing'!U10="Low Margin","Increase price toward "&TEXT('Menu Pricing'!R10,"$0.00")&" or reduce ingredient cost to hit target margin",IF('Menu Pricing'!U10="Needs Review","Review pricing — close to target but not yet there","Performing well — protect quality and keep promoting"))) -> Increase price toward $0.00 or reduce ingredient cost to hit target margin | D10: =MAX(0,'Menu Pricing'!R10-'Menu Pricing'!J10)*SUMIFS(Sales!$C$5:$C$124,Sales!$B$5:$B$124,B10) -> 0

Sheet Restaurant Health Score
A1: Restaurant Health Score
A2: A single 0–100 score combining ten weighted profitability factors.
A4: Factor | B4: Weight | C4: Raw Metric | D4: Score (0-100) | E4: Weighted Score
A5: Food Cost | B5: 0.2 | C5: =AVERAGE('Menu Pricing'!$O$5:$O$10) -> 0 | D5: =MIN(100,MAX(0,100*(2-(C5/'Business Profile'!$B$9)))) -> 100 | E5: =D5*B5 -> 20
A6: Net Margin | B6: 0.2 | C6: =AVERAGE('Menu Pricing'!$N$5:$N$10) -> 0 | D6: =MIN(100,MAX(0,100*(C6/'Business Profile'!$B$11))) -> 0 | E6: =D6*B6 -> 0
A7: Gross Margin | B7: 0.1 | C7: =AVERAGE('Menu Pricing'!$L$5:$L$10) -> 0 | D7: =MIN(100,MAX(0,100*(C7/'Business Profile'!$B$10))) -> 0 | E7: =D7*B7 -> 0
A8: Waste % | B8: 0.1 | C8: =AVERAGE('Ingredients Database'!$G$5:$G$16) -> 0 | D8: =MIN(100,MAX(0,100*(1-C8/0.15))) -> 100 | E8: =D8*B8 -> 10
A9: Packaging Cost Ratio | B9: 0.05 | C9: =IFERROR(AVERAGE('Menu Pricing'!$D$5:$D$10)/AVERAGE('Menu Pricing'!$J$5:$J$10),0) -> 0 | D9: =MIN(100,MAX(0,100*(1-C9/0.2))) -> 100 | E9: =D9*B9 -> 5
A10: Overhead Ratio | B10: 0.1 | C10: =IFERROR('Operating Expenses'!$B$20/'Business Profile'!$B$13,0) -> 0 | D10: =MIN(100,MAX(0,100*(1-C10/0.6))) -> 100 | E10: =D10*B10 -> 10
A11: Profitability (items not losing money) | B11: 0.1 | C11: =COUNTIF('Menu Pricing'!$M$5:$M$10,">=0")/COUNTA('Menu Pricing'!$A$5:$A$10) -> 1 | D11: =C11*100 -> 100 | E11: =D11*B11 -> 10
A12: Pricing Accuracy (at/above recommended) | B12: 0.05 | C12: =COUNTIF('Menu Pricing'!$T$5:$T$10,">=0")/COUNTA('Menu Pricing'!$A$5:$A$10) -> 1 | D12: =C12*100 -> 100 | E12: =D12*B12 -> 5
A13: Inventory Health (stock above minimum) | B13: 0.05 | C13: =SUMPRODUCT(('Ingredients Database'!$I$5:$I$16>='Ingredients Database'!$J$5:$J$16)*1)/COUNTA('Ingredients Database'!$A$5:$A$16) -> 1 | D13: =C13*100 -> 100 | E13: =D13*B13 -> 5
A14: Low-Margin Item Share (Excellent/Healthy) | B14: 0.05 | C14: =(COUNTIF('Menu Pricing'!$U$5:$U$10,"Excellent")+COUNTIF('Menu Pricing'!$U$5:$U$10,"Healthy"))/COUNTA('Menu Pricing'!$A$5:$A$10) -> 0 | D14: =C14*100 -> 0 | E14: =D14*B14 -> 0
A16: RESTAURANT HEALTH SCORE | D16: =SUM(E5:E14) -> 65
A17: Performance Level | D17: =IF(D16>=90,"Excellent",IF(D16>=75,"Healthy",IF(D16>=60,"Needs Attention",IF(D16>=40,"Poor","Critical")))) -> Needs Attention
